notifierbot/__init__.py
notifierbot/telegram/__init__.py
notifierbot/telegram/bot.py
notifierbot/telegram/config.py
notifierbot/telegram/tf_callback.py
tests/__init__.py
tests/telegram_bot_test.py
notifierbot-1.2.0.dist-info/LICENSE.txt
notifierbot-1.2.0.dist-info/METADATA
notifierbot-1.2.0.dist-info/WHEEL
notifierbot-1.2.0.dist-info/top_level.txt
notifierbot-1.2.0.dist-info/RECORD
